{
  "info": {
    "_postman_id": "68d75c66-3358-4077-b45d-be7ec0f998a9",
    "name": "simple-rag",
    "schema": "https://schema.getpostman.com/json/collection/v2.1.0/collection.json",
    "_exporter_id": "51802644",
    "_collection_link": "https://go.postman.co/collection/51802644-68d75c66-3358-4077-b45d-be7ec0f998a9?source=collection_link"
  },
  "item": [
    {
      "name": "welcome-request",
      "request": {
        "method": "GET",
        "header": [],
        "url": {
          "raw": "{{api}}/api/v1/",
          "host": [
            "{{api}}"
          ],
          "path": [
            "api",
            "v1",
            ""
          ]
        }
      },
      "response": []
    },
    {
      "name": "upload",
      "request": {
        "method": "POST",
        "header": [],
        "body": {
          "mode": "formdata",
          "formdata": [
            {
              "key": "file",
              "type": "file",
              "uuid": "1cbce48d-6d46-4e9d-9fed-d6fd0d5cd40e",
              "src": "/home/essam/Desktop/jay_leno.pdf"
            }
          ]
        },
        "url": {
          "raw": "{{api}}/api/v1/data/upload/1",
          "host": [
            "{{api}}"
          ],
          "path": [
            "api",
            "v1",
            "data",
            "upload",
            "1"
          ]
        }
      },
      "response": []
    },
    {
      "name": "process",
      "request": {
        "method": "POST",
        "header": [],
        "body": {
          "mode": "raw",
          "raw": "{\n    // \"file_id\": \"7\",\n    \"chunk_size\": 200,\n    \"overlap_size\": 20,\n    \"do_reset\": 1\n}",
          "options": {
            "raw": {
              "language": "json"
            }
          }
        },
        "url": {
          "raw": "{{api}}/api/v1/data/process/1",
          "host": [
            "{{api}}"
          ],
          "path": [
            "api",
            "v1",
            "data",
            "process",
            "1"
          ]
        }
      },
      "response": []
    },
    {
      "name": "nlp_index_push",
      "request": {
        "method": "POST",
        "header": [],
        "body": {
          "mode": "raw",
          "raw": "{\n    \"do_reset\": 1\n}",
          "options": {
            "raw": {
              "language": "json"
            }
          }
        },
        "url": {
          "raw": "{{api}}/api/v1/nlp/index/push/1",
          "host": [
            "{{api}}"
          ],
          "path": [
            "api",
            "v1",
            "nlp",
            "index",
            "push",
            "1"
          ]
        }
      },
      "response": []
    },
    {
      "name": "nlp_index_info",
      "protocolProfileBehavior": {
        "disableBodyPruning": true
      },
      "request": {
        "method": "GET",
        "header": [],
        "body": {
          "mode": "raw",
          "raw": "{\n    \"text\": \"When was Jay Leno was born?\"\n}\n",
          "options": {
            "raw": {
              "language": "json"
            }
          }
        },
        "url": {
          "raw": "{{api}}/api/v1/nlp/index/info/1",
          "host": [
            "{{api}}"
          ],
          "path": [
            "api",
            "v1",
            "nlp",
            "index",
            "info",
            "1"
          ]
        }
      },
      "response": []
    },
    {
      "name": "nlp_index_search",
      "request": {
        "method": "POST",
        "header": [],
        "body": {
          "mode": "raw",
          "raw": "{\n    \"text\": \"When was Jay Leno was born?\",\n    \"limit\": 5\n}",
          "options": {
            "raw": {
              "language": "json"
            }
          }
        },
        "url": {
          "raw": "{{api}}/api/v1/nlp/index/search/1",
          "host": [
            "{{api}}"
          ],
          "path": [
            "api",
            "v1",
            "nlp",
            "index",
            "search",
            "1"
          ]
        }
      },
      "response": []
    },
    {
      "name": "nlp-rag-answer",
      "request": {
        "method": "POST",
        "header": [],
        "body": {
          "mode": "raw",
          "raw": "{\n    \"text\": \"When was Jay Leno was born?\",\n    \"limit\": 5\n}",
          "options": {
            "raw": {
              "language": "json"
            }
          }
        }
      },
      "response": []
    }
  ],
  "event": [
    {
      "listen": "prerequest",
      "script": {
        "type": "text/javascript",
        "packages": {},
        "requests": {},
        "exec": [
          ""
        ]
      }
    },
    {
      "listen": "test",
      "script": {
        "type": "text/javascript",
        "packages": {},
        "requests": {},
        "exec": [
          ""
        ]
      }
    }
  ],
  "variable": [
    {
      "key": "api",
      "value": ""
    }
  ]
}